examples/__init__.py
examples/evaluate_random_space_invaders.py
examples/play_windy_grid_world.py
examples/train_dqn_pursuit.py
examples/train_hga3c_space_invaders.py
examples/character_recognition/ConvNetForOCRDataset.py
examples/character_recognition/OCRDataset.py
examples/character_recognition/__init__.py
examples/character_recognition/tests.py
examples/pursuit/__init__.py
examples/pursuit/tests.py
examples/pursuit/agents/GreedyAgent.py
examples/pursuit/agents/ProbabilisticDestinationsAgent.py
examples/pursuit/agents/PursuitTeammate.py
examples/pursuit/agents/TeammateAwareAgent.py
examples/pursuit/agents/__init__.py
examples/pursuit/environment/Pursuit.py
examples/pursuit/environment/PursuitState.py
examples/pursuit/environment/PyGameVisualizer.py
examples/pursuit/environment/__init__.py
examples/pursuit/environment/utils.py
examples/pursuit/metrics/PreyCapturesEveryTimestepIntervalMetric.py
examples/pursuit/metrics/TotalPreyCapturesMetric.py
examples/pursuit/metrics/__init__.py
examples/pursuit/search/PursuitMCTSNode.py
examples/pursuit/search/__init__.py
examples/pursuit/search/astar.py
tests/__init__.py
tests/test_metrics.py
tests/test_runners.py
tests/environment_tests/__init__.py
tests/environment_tests/test_mdps.py
tests/environment_tests/test_wrappers.py
yaaf/__init__.py
yaaf/agents/Agent.py
yaaf/agents/GreedyAgent.py
yaaf/agents/HumanAgent.py
yaaf/agents/QLearningAgent.py
yaaf/agents/RandomAgent.py
yaaf/agents/SARSAAgent.py
yaaf/agents/__init__.py
yaaf/agents/dqn/DQNAgent.py
yaaf/agents/dqn/__init__.py
yaaf/agents/dqn/networks.py
yaaf/agents/hga3c/ActorCriticNetwork.py
yaaf/agents/hga3c/HybridGA3CAgent.py
yaaf/agents/hga3c/HybridGA3CLogger.py
yaaf/agents/hga3c/PredictorThread.py
yaaf/agents/hga3c/TrainerThread.py
yaaf/agents/hga3c/WorkerAgent.py
yaaf/agents/hga3c/__init__.py
yaaf/environments/__init__.py
yaaf/environments/markov/CliffWalkMDP.py
yaaf/environments/markov/MarkovDecisionProcess.py
yaaf/environments/markov/WindyGridWorldMDP.py
yaaf-1.1.0.dist-info/LICENSE
yaaf-1.1.0.dist-info/METADATA
yaaf-1.1.0.dist-info/WHEEL
yaaf-1.1.0.dist-info/top_level.txt
yaaf-1.1.0.dist-info/RECORD
