Metadata-Version: 2.1
Name: yaaf
Version: 1.1.0
Summary: YAAF: Yet Another Agents Framework
Home-page: http://github.com/jmribeiro/yaaf
Author: João Ribeiro
Author-email: joao.g.ribeiro@tecnico.ulisboa.pt
License: Apache 2.0
Keywords: Autonomous Agents,Reinforcement Learning,Deep Learning
Platform: UNKNOWN
Classifier: Programming Language :: Python :: 3
Requires-Dist: numpy
Requires-Dist: matplotlib
Requires-Dist: gym
Requires-Dist: torch
Requires-Dist: torchvision
Requires-Dist: tensorflow
Requires-Dist: sklearn
Requires-Dist: pyyaml
Requires-Dist: pyparsing
Requires-Dist: tqdm
